pyfury/__init__.pxd
pyfury/__init__.py
pyfury/_fury.py
pyfury/_serialization.pyx
pyfury/_serialization.so
pyfury/_serializer.py
pyfury/_struct.py
pyfury/_util.pxd
pyfury/_util.pyx
pyfury/_util.so
pyfury/buffer.py
pyfury/codegen.py
pyfury/error.py
pyfury/resolver.py
pyfury/serializer.py
pyfury/type.py
pyfury/util.py
pyfury/format/__init__.py
pyfury/format/_format.pyx
pyfury/format/_format.so
pyfury/format/encoder.py
pyfury/format/infer.py
pyfury/format/serializer.py
pyfury/includes/__init__.pxd
pyfury/includes/libabsl.pxd
pyfury/includes/libformat.pxd
pyfury/includes/libutil.pxd
pyfury/lib/__init__.pxd
pyfury/lib/mmh3/__init__.pxd
pyfury/lib/mmh3/__init__.py
pyfury/lib/mmh3/mmh3.pxd
pyfury/lib/mmh3/mmh3.pyx
pyfury/lib/mmh3/mmh3.so
pyfury-0.10.3.dist-info/METADATA
pyfury-0.10.3.dist-info/WHEEL
pyfury-0.10.3.dist-info/top_level.txt
pyfury-0.10.3.dist-info/RECORD
