Metadata-Version: 2.1
Name: pyfury
Version: 0.10.3
Summary: Apache Fury™(incubating) is a blazingly fast multi-language serialization framework powered by jit and zero-copy
Author-email: chaokunyang <shawn.ck.yang@gmail.com>
Maintainer-email: "https://github.com/chaokunyang" <shawn.ck.yang@gmail.com>
Keywords: fury,serialization,multi-language,fast,row-format,jit,codegen,polymorphic,zero-copy
Classifier: License :: OSI Approved :: Apache Software License
Classifier: Development Status :: 4 - Beta
Classifier: Programming Language :: Python :: 3.8
Classifier: Programming Language :: Python :: 3.9
Classifier: Programming Language :: Python :: 3.10
Classifier: Programming Language :: Python :: 3.11
Classifier: Programming Language :: Python :: 3.12
Classifier: Programming Language :: Python :: Implementation :: CPython
Requires-Dist: cloudpickle
Provides-Extra: all
Requires-Dist: pyarrow; extra == "all"
Provides-Extra: format
Requires-Dist: pyarrow; extra == "format"
